nonebot_plugin_nearcade_reporter/__init__.py
nonebot_plugin_nearcade_reporter/command/__init__.py
nonebot_plugin_nearcade_reporter/command/query.py
nonebot_plugin_nearcade_reporter/command/search.py
nonebot_plugin_nearcade_reporter/command/update.py
nonebot_plugin_nearcade_reporter/config.py
nonebot_plugin_nearcade_reporter/errors.py
nonebot_plugin_nearcade_reporter/network.py
nonebot_plugin_nearcade_reporter/safe_dict.py
nonebot_plugin_nearcade_reporter-0.1.8.dist-info/licenses/LICENSE
nonebot_plugin_nearcade_reporter-0.1.8.dist-info/METADATA
nonebot_plugin_nearcade_reporter-0.1.8.dist-info/WHEEL
nonebot_plugin_nearcade_reporter-0.1.8.dist-info/RECORD
