Metadata-Version: 2.4
Name: nonebot-plugin-nearcade-reporter
Version: 0.1.8
Summary: Nearcade Reporter Plugin
License-File: LICENSE
Author: jiyun233
Author-email: koishi@origin.pw
Requires-Python: >=3.9
Classifier: Programming Language :: Python :: 3
Classifier: Programming Language :: Python :: 3.9
Classifier: Programming Language :: Python :: 3.10
Classifier: Programming Language :: Python :: 3.11
Classifier: Programming Language :: Python :: 3.12
Classifier: Programming Language :: Python :: 3.13
Classifier: Programming Language :: Python :: 3.14
Provides-Extra: onebot
Requires-Dist: httpx (>=0.27.0,<0.28.0)
Requires-Dist: nonebot2 (>=2.2.0,<3.0.0)
